dscc_sdd_client/__init__.py
dscc_sdd_client/client.py
dscc_sdd_client-0.0.1.dist-info/LICENSE
dscc_sdd_client-0.0.1.dist-info/METADATA
dscc_sdd_client-0.0.1.dist-info/WHEEL
dscc_sdd_client-0.0.1.dist-info/top_level.txt
dscc_sdd_client-0.0.1.dist-info/RECORD
