Metadata-Version: 2.1
Name: dscc-sdd-client
Version: 0.0.1
Summary: A client to interact with the DSCC SDD server.
Home-page: https://github.com/dscc-admin/dscc_sdd/
Author: Data Science Competence Center, Swiss Federal Statistical Office
Author-email: dscc@bfs.admin.ch
License: MIT
Keywords: opendp,smartnoise-sql,logger,ast
Classifier: Development Status :: 3 - Alpha
Classifier: Intended Audience :: Developers
Classifier: License :: OSI Approved :: MIT License
Classifier: Programming Language :: Python :: 3.8
Classifier: Programming Language :: Python :: 3.9
Requires-Python: >=3.8, <4
License-File: LICENSE
Requires-Dist: opendp ==0.8.0
Requires-Dist: numpy ==1.22.3
Requires-Dist: requests ==2.31.0
Requires-Dist: pandas ==2.0.1
Requires-Dist: pyyaml
